<?xml version="1.0" encoding="utf-8"?>
<odoo>
    <record id="ir_exports_form_view" model="ir.ui.view">
        <field name="model">ir.exports</field>
        <field name="inherit_id" ref="base_export_manager.ir_exports_form_view"/>
        <field name="arch" type="xml">
            <xpath expr="//form/group[1]" position="before">
                <header>
                    <button name="%(import_pattern_wizard_action)d" string="Import" class="oe_highlight" type="action" context="{'default_ir_exports_id': id, 'hide_ir_export_id': True}"/>
                    <button name="generate_pattern" string="Generate Pattern" class="oe_highlight" type="object"/>
                </header>
                <div class="oe_button_box" name="button_box">
                    <button name="button_open_pattimpex_fail" type="object" class="oe_stat_button" icon="fa-thumbs-o-down">
                        <div class="o_field_widget o_stat_info">
                            <span class="o_stat_value">
                                <field name="count_pattimpex_fail" widget="statinfo" nolabel="1"/>
                            </span>
                            <span class="o_stat_text">Fail</span>
                        </div>
                    </button>
                    <button name="button_open_pattimpex_pending" type="object" class="oe_stat_button" icon="fa-spinner">
                        <div class="o_field_widget o_stat_info">
                            <span class="o_stat_value">
                                <field name="count_pattimpex_pending" widget="statinfo" nolabel="1"/>
                            </span>
                            <span class="o_stat_text">Pending</span>
                        </div>
                    </button>
                    <button name="button_open_pattimpex_success" type="object" class="oe_stat_button" icon="fa-thumbs-o-up">
                        <div class="o_field_widget o_stat_info">
                            <span class="o_stat_value">
                                <field name="count_pattimpex_success" widget="statinfo" nolabel="1"/>
                            </span>
                            <span class="o_stat_text">Success</span>
                        </div>
                    </button>
                </div>

            </xpath>
            <xpath expr="//form/group[1]" position="after">
                <group name="general_info">
                    <field name="export_format" required="True"/>
                    <field name="pattern_file" filename="pattern_file_name"/>
                    <field name="pattern_file_name" invisible="1"/>
                    <field name="pattern_last_generation_date"/>
                    <field name="id" invisible="1"/>
                    <field name="partial_commit"/>
                    <field name="flush_step"/>
                    <field name="use_description"/>
                    <field name="is_pattern" invisible="1"/>
                </group>
            </xpath>
            <xpath expr="//field[@name='field2_id']" position="attributes">
                <attribute name="attrs">{
                    'readonly': [('hidden_fields', 'ilike', 'field2_id')],
                    'required': [('required_fields', 'ilike', 'field2_id')]
                }</attribute>
            </xpath>
            <xpath expr="//field[@name='field3_id']" position="attributes">
                <attribute name="attrs">{
                    'readonly': [('hidden_fields', 'ilike', 'field3_id')],
                    'required': [('required_fields', 'ilike', 'field3_id')]
                }</attribute>
            </xpath>
            <xpath expr="//field[@name='field4_id']" position="attributes">
                <attribute name="attrs">{
                    'readonly': [('hidden_fields', 'ilike', 'field4_id')],
                    'required': [('required_fields', 'ilike', 'field4_id')]
                }</attribute>
            </xpath>
            <xpath expr="//field[@name='field4_id']" position="after">
                <field name="is_key"/>
                <field name="required_fields" invisible="1"/>
                <field name="hidden_fields" invisible="1"/>
                <field name="number_occurence" attrs="{
                    'required': [('required_fields', 'ilike', 'number_occurence')],
                    'readonly': [('hidden_fields', 'ilike', 'number_occurence')],
                    'invisible': [('hidden_fields', 'ilike', 'number_occurence')]}"/>
                <field name="pattern_export_id" attrs="{
                    'required': [('required_fields', 'ilike', 'pattern_export_id')],
                    'readonly': [('hidden_fields', 'ilike', 'pattern_export_id')],
                    'invisible': [('hidden_fields', 'ilike', 'pattern_export_id')]}"/>
                <field name="related_model_id" invisible="1"/>
                <field name="last_field_id" invisible="1"/>
                <field name="add_select_tab"
                       attrs="{
                       'invisible': [('hidden_fields', 'ilike', 'add_select_tab')],
                       'readonly': [('hidden_fields', 'ilike', 'add_select_tab')]
                       }"
                />
                <field name="related_model_name" invisible="1"/>
                <field name="tab_filter_id"
                       domain="[('model_id', '=', related_model_name)]"
                       attrs="{
                       'invisible': [('hidden_fields', 'ilike', 'tab_filter_id')],
                       'readonly': [('hidden_fields', 'ilike', 'tab_filter_id')]
                       }"/>
            </xpath>
        </field>
    </record>
</odoo>
